odoo/addons/sale_order_amount_to_invoice/README.rst
odoo/addons/sale_order_amount_to_invoice/__init__.py
odoo/addons/sale_order_amount_to_invoice/__manifest__.py
odoo/addons/sale_order_amount_to_invoice/i18n/es.po
odoo/addons/sale_order_amount_to_invoice/i18n/it.po
odoo/addons/sale_order_amount_to_invoice/i18n/sale_order_amount_to_invoice.pot
odoo/addons/sale_order_amount_to_invoice/models/__init__.py
odoo/addons/sale_order_amount_to_invoice/models/sale_order.py
odoo/addons/sale_order_amount_to_invoice/readme/CONFIGURE.md
odoo/addons/sale_order_amount_to_invoice/readme/CONTEXT.md
odoo/addons/sale_order_amount_to_invoice/readme/CONTRIBUTORS.md
odoo/addons/sale_order_amount_to_invoice/readme/DESCRIPTION.md
odoo/addons/sale_order_amount_to_invoice/readme/USAGE.md
odoo/addons/sale_order_amount_to_invoice/static/description/icon.png
odoo/addons/sale_order_amount_to_invoice/static/description/index.html
odoo/addons/sale_order_amount_to_invoice/tests/__init__.py
odoo/addons/sale_order_amount_to_invoice/tests/test_sale_order_invoice_amount.py
odoo/addons/sale_order_amount_to_invoice/views/sale_order_view.xml
odoo14_addon_sale_order_amount_to_invoice-14.0.1.0.1.dev6.dist-info/METADATA
odoo14_addon_sale_order_amount_to_invoice-14.0.1.0.1.dev6.dist-info/WHEEL
odoo14_addon_sale_order_amount_to_invoice-14.0.1.0.1.dev6.dist-info/top_level.txt
odoo14_addon_sale_order_amount_to_invoice-14.0.1.0.1.dev6.dist-info/RECORD
